{
    "kir_sim.ode": {
        "comments": [
            "% Spike adaptation by erg-like K+ current.  If girbar is altered (0.5->0), \n% spike discharge will be changed.  \n% Written by Dr. Sheng-Nan Wu, Dept Physiol, Natl Cheng Kung U Med Coll.\n% Ref: Chiesa et al., J Physiol 1997;501:313-318\n\n% Initial values of the variables\ninit v=-72.0, nK=0.288, hK=0.367, mNa=0.041,  hNa=0.844, nIR=0.003, rIR=0.282\n\n% Values of the model parameters\nparams iapp=1.2, cm=1, gnabar=15, gkbar=2.5, girbar=0.5, gl=0.05, vna=50, vk=-80, vir=-80, vl=-80\n\n% Gating functions\nalphaNam(v) = 0.1*(v+40)/( 1 - exp(-0.09*(v+40)))\nbetaNam(v) =  4*exp(-0.055*(v+70))\nmNainf(v) = 1/(1+betaNam(v)/alphaNam(v))\ntauNam(v) = 1/(alphaNam(v) + betaNam(v))\n\nalphaNah(v) =  0.07*exp(-0.05*(v+70))\nbetaNah(v) = 1/( 1 + exp(-0.09*(v+25)) )\nhNainf(v) = 1/(1+betaNah(v)/alphaNah(v))\ntauNah(v) = 1/(alphaNah(v) + betaNah(v))\n\nalphaKn(v) = 0.01*(v + 60)/(1 - exp(-0.1*(V + 60)))\nbetaKn(v) = 0.125*exp(-0.0125*(V + 70))\nnKinf(v) = 1/(1+betaKn(v)/alphaKn(v))\ntauKn(v) = 1/(alphaKn(v) + betaKn(v))\n\nalphaKh(v) = 0.001*exp(-0.04*(v+70))\nbetaKh(v) = 0.001*exp(-0.0195*(v+40))\nhKinf(v) = 1/(1+betaKh(v)/alphaKh(v))\ntauKh(v) = 1/(alphaKh(v) + betaKh(v))\n\nalphaIRn(v) = 0.09/(1+exp(0.11*(v+100)))\nbetaIRn(v) = 0.00035*exp(0.07*(v+25))\nnIRinf(v) = 1/(1+betaIRn(v)/alphaIRn(v))\ntauIRn(v) = 1/(alphaIRn(v) + betaIRn(v))\n\nalphaIRr(v) = 30/(1+exp(0.04*(v+230)))\nbetaIRr(v) = 0.15/(1+exp(-0.05*(v+120)))\nrIRinf(v) = 1/(1+betaIRr(v)/alphaIRr(v))\ntauIRr(v) = 1/(alphaIRr(v) + betaIRr(v))\n\n% Apply current injection\npar tpulse=610\npar tfirst=10\nistim = iapp*(heav(t-tfirst)-heav(t-tpulse))\n\n% The differential equations\nv' =  -(gnabar*mNa^3*hNa*(v-vna) + gkbar*nK^4*hK*(v-vk) + girbar*nIR*rIR*(v-vir) + gl*(v-vl) - istim)/cm\nmNa' =  (mNainf(v) - mNa)/tauNam(v)\nhNa' =  (hNainf(v) - hNa)/tauNah(v)\nnK' =  (nKinf(v) - nK)/tauKn(v)\nhK' = (hKinf(v) - hK)/tauKh(v)\nnIR' = (nIRinf(v) - nIR)/tauIRn(v)\nrIR' = (rIRinf(v) - rIR)/tauIRr(v)\n\n% Numerical and plotting parameters for xpp\n@xlo=0, xhi=700, ylo=-90, yhi=+60, total=700, dt=0.05, method=Euler, LT=1\nd\n"
        ],
        "variables": [
            "tauKh",
            "of",
            "betaNam",
            "Natl",
            "Euler",
            "total",
            "Wu",
            "xhi",
            "alphaKn",
            "differential",
            "dt",
            "the",
            "betaKh",
            "LT",
            "gl",
            "Written",
            "changed",
            "Dr",
            "Dept",
            "vna",
            "equations",
            "vl",
            "Cheng",
            "If",
            "iapp",
            "V",
            "tpulse",
            "vir",
            "Ref",
            "hNainf",
            "hNa",
            "gkbar",
            "Med",
            "injection",
            "init",
            "current",
            "et",
            "and",
            "rIR",
            "vk",
            "betaIRr",
            "cm",
            "alphaKh",
            "xpp",
            "The",
            "betaNah",
            "betaIRn",
            "al",
            "tauNah",
            "alphaIRr",
            "erg",
            "istim",
            "variables",
            "will",
            "J",
            "alphaNah",
            "Physiol",
            "hK",
            "ylo",
            "method",
            "nIRinf",
            "parameters",
            "gnabar",
            "v",
            "spike",
            "t",
            "exp",
            "hKinf",
            "rIRinf",
            "discharge",
            "xlo",
            "Spike",
            "par",
            "yhi",
            "model",
            "Values",
            "Apply",
            "nKinf",
            "heav",
            "be",
            "Initial",
            "tauNam",
            "values",
            "Chiesa",
            "is",
            "Numerical",
            "U",
            "Nan",
            "alphaIRn",
            "nIR",
            "functions",
            "tauIRn",
            "altered",
            "params",
            "for",
            "alphaNam",
            "by",
            "mNainf",
            "adaptation",
            "nK",
            "mNa",
            "tauKn",
            "tauIRr",
            "Coll",
            "Gating",
            "d",
            "Kung",
            "plotting",
            "betaKn",
            "K",
            "Sheng",
            "tfirst",
            "like",
            "girbar"
        ]
    },
    "readme.txt": {
        "comments": [
            "This is the readme.txt for the model associated with the paper\n\nChiesa N, Rosati B, Arcangeli A, Olivotto M, Wanke E. A novel role \nfor HERG K+ channels: spike-frequency adaptation. J Physiol 1997;501:313-318\n\nAbstract:\n1. The regular firing of a Hodgkin-Huxley neurone endowed with fast Na+ \nand delayed K+ channels can be converted into adapting firing by appending \nHERG (human eag-related gene) channels. 2. The computer model predictions \nwere verified by studying the firing properties of F-11 DRG neurone x \nneuroblastoma hybrid cells induced to differentiate by long- term exposure \nto retinoic acid. These cells, which express HERG currents (IHERG), show \nclear spike-frequency adaptation of their firing when current clamped with \nlong depolarizations. 3. In agreement with the prediction, the selective \nblocking of IHERG by class III antiarrhythmic drugs always led to the \ndisappearance of the spike- frequency adaptation, and the conversion of \nadapting firing to regular firing. 4. It is proposed that, in addition to their \nrole in the repolarization of the heart action potential, HERG channels may \nsustain a process of spike-frequency adaptation, and hence contribute to the \ncontrol of burst duration in a way that is similar to that of the K+ currents, \nIAHP, IC and IM. In addition to the known cardiac arrhythmia syndrome \n(LQT2), genetic mutations or an altered HERG expression could lead to \ncontinuous hyperexcitable states sustained by the inability of nerve or endocrine \ncells to accommodate to repetitive stimuli. This might help in clarifying the \npathogenesis of still undefined idiopathic familial epilepsies. \n---\n\nTo run the models:\nXPP: start with the command\n\nxpp ode\\kir_sim.ode\n\nMouse click on Initialconds, and then (G)o.\nThis makes a trace similar to fig 1E of the paper.\n\nRegarding xpp program, please contact with \nBard Ermentrout's website http://www.pitt.edu/~phase/\ndescribes how to get and use xpp (Bard wrote xpp).\n\nThese model files were submitted by:\n\nDr. Sheng-Nan Wu\nDept Physiol\nNatl Cheng Kung U Med Coll\nTainan 70101, Taiwan\n\nsnwu@mail.ncku.edu.tw\n\n",
            ""
        ],
        "variables": [
            "of",
            "kir_sim",
            "These",
            "nerve",
            "can",
            "in",
            "contact",
            "undefined",
            "Ermentrout",
            "wrote",
            "help",
            "burst",
            "Natl",
            "tw",
            "website",
            "This",
            "repolarization",
            "Wu",
            "conversion",
            "genetic",
            "adapting",
            "Regarding",
            "paper",
            "led",
            "addition",
            "the",
            "known",
            "hyperexcitable",
            "or",
            "makes",
            "s",
            "HERG",
            "Abstract",
            "exposure",
            "E",
            "disappearance",
            "with",
            "trace",
            "potential",
            "Dr",
            "endowed",
            "Dept",
            "how",
            "continuous",
            "antiarrhythmic",
            "Cheng",
            "edu",
            "heart",
            "get",
            "use",
            "selective",
            "Med",
            "properties",
            "LQT2",
            "ode",
            "clear",
            "differentiate",
            "current",
            "and",
            "firing",
            "term",
            "files",
            "could",
            "proposed",
            "Arcangeli",
            "Rosati",
            "a",
            "click",
            "studying",
            "xpp",
            "models",
            "The",
            "converted",
            "lead",
            "describes",
            "hence",
            "Taiwan",
            "that",
            "then",
            "retinoic",
            "IM",
            "induced",
            "B",
            "fig",
            "computer",
            "agreement",
            "phase",
            "J",
            "acid",
            "Physiol",
            "Hodgkin",
            "class",
            "an",
            "IAHP",
            "readme",
            "inability",
            "cells",
            "submitted",
            "long",
            "fast",
            "sustained",
            "spike",
            "duration",
            "expression",
            "stimuli",
            "command",
            "endocrine",
            "clarifying",
            "IHERG",
            "their",
            "action",
            "frequency",
            "x",
            "mutations",
            "pathogenesis",
            "eag",
            "F",
            "http",
            "N",
            "start",
            "gene",
            "on",
            "drugs",
            "model",
            "depolarizations",
            "channels",
            "currents",
            "be",
            "contribute",
            "In",
            "DRG",
            "o",
            "may",
            "program",
            "M",
            "III",
            "A",
            "Chiesa",
            "Tainan",
            "is",
            "which",
            "Mouse",
            "neuroblastoma",
            "related",
            "familial",
            "please",
            "U",
            "cardiac",
            "Nan",
            "To",
            "idiopathic",
            "hybrid",
            "delayed",
            "pitt",
            "run",
            "Olivotto",
            "mail",
            "snwu",
            "altered",
            "prediction",
            "process",
            "for",
            "sustain",
            "arrhythmia",
            "show",
            "predictions",
            "clamped",
            "repetitive",
            "It",
            "neurone",
            "by",
            "syndrome",
            "to",
            "adaptation",
            "associated",
            "epilepsies",
            "into",
            "novel",
            "way",
            "txt",
            "role",
            "G",
            "Coll",
            "human",
            "Wanke",
            "express",
            "states",
            "Huxley",
            "Initialconds",
            "similar",
            "still",
            "control",
            "were",
            "appending",
            "Kung",
            "IC",
            "always",
            "accommodate",
            "when",
            "might",
            "XPP",
            "Bard",
            "K",
            "Sheng",
            "www",
            "blocking",
            "verified",
            "Na",
            "regular",
            "ncku"
        ]
    }
}